simple_idealized_1d_nlse/__init__.py
simple_idealized_1d_nlse/cli.py
simple_idealized_1d_nlse/core/__init__.py
simple_idealized_1d_nlse/core/initial_conditions.py
simple_idealized_1d_nlse/core/solver.py
simple_idealized_1d_nlse/io/__init__.py
simple_idealized_1d_nlse/io/config_manager.py
simple_idealized_1d_nlse/io/data_handler.py
simple_idealized_1d_nlse/utils/__init__.py
simple_idealized_1d_nlse/utils/logger.py
simple_idealized_1d_nlse/utils/timer.py
simple_idealized_1d_nlse/visualization/__init__.py
simple_idealized_1d_nlse/visualization/animator.py
simple_idealized_1d_nlse-0.0.4.dist-info/LICENSE.txt
simple_idealized_1d_nlse-0.0.4.dist-info/METADATA
simple_idealized_1d_nlse-0.0.4.dist-info/WHEEL
simple_idealized_1d_nlse-0.0.4.dist-info/entry_points.txt
simple_idealized_1d_nlse-0.0.4.dist-info/RECORD
