Metadata-Version: 2.3
Name: simple-idealized-1d-nlse
Version: 0.0.4
Summary: A flexible and efficient solver for the 1D Nonlinear Schrödinger Equation
License: WTFPL
Author: Sandy H. S. Herho
Author-email: sandy.herho@email.ucr.edu
Requires-Python: >=3.8,<4.0
Classifier: License :: Other/Proprietary License
Classifier: Programming Language :: Python :: 3
Classifier: Programming Language :: Python :: 3.8
Classifier: Programming Language :: Python :: 3.9
Classifier: Programming Language :: Python :: 3.10
Classifier: Programming Language :: Python :: 3.11
Classifier: Programming Language :: Python :: 3.12
Classifier: Programming Language :: Python :: 3.13
Requires-Dist: matplotlib
Requires-Dist: netCDF4
Requires-Dist: numpy
Requires-Dist: pyyaml
Requires-Dist: scipy
Requires-Dist: tqdm
